{
  "version": "0.1.0",
  "type": "model",
  "fields": {
    "id": {
      "type": "int",
      "dbField": "topicid"
    },
    "statusid": {
      "type": "int",
      "json": "stid"
    },
    "userid": {
      "type": "int",
      "json": "uid"
    },
    "dateline": {
      "type": "date",
      "json": "dl"
    },
    "isprivate": {
      "type": "bool",
      "json": "prv"
    },
    "title": {
      "type": "string",
      "json": "tl"
    },
    "body": {
      "type": "string",
      "json": "bd"
    },
    "pubkey": {
      "type": "string",
      "json": "pk"
    },
    "viewcount": {
      "type": "int",
      "json": "vcnt"
    },
    "upddate": {
      "type": "date",
      "json": "upd"
    },
    "status": {
      "type": "model:TopicStatus",
      "json": "st",
      "notNULL": true
    },
    "statuses": {
      "type": "modelList:TopicStatusList",
      "json": "sts"
    },
    "commentStatistic": {
      "type": "model:comment:Statistic",
      "json": "cmtstat"
    },
    "files": {
      "type": "modelList:FileList"
    }
  }
}